ccxt/_1btcxe.py
ccxt/__init__.py
ccxt/acx.py
ccxt/allcoin.py
ccxt/anxpro.py
ccxt/anybits.py
ccxt/bcex.py
ccxt/bequant.py
ccxt/bibox.py
ccxt/bigone.py
ccxt/biki.py
ccxt/binance.py
ccxt/binance2.py
ccxt/binanceje.py
ccxt/bit2c.py
ccxt/bitbank.py
ccxt/bitbay.py
ccxt/bitfinex.py
ccxt/bitfinex2.py
ccxt/bitflyer.py
ccxt/bitforex.py
ccxt/bithumb.py
ccxt/bitibu.py
ccxt/bitinka.py
ccxt/bitkk.py
ccxt/bitlish.py
ccxt/bitmarket.py
ccxt/bitmart.py
ccxt/bitmex.py
ccxt/bitsane.py
ccxt/bitso.py
ccxt/bitstamp.py
ccxt/bitstamp1.py
ccxt/bittrex.py
ccxt/bitz.py
ccxt/bl3p.py
ccxt/bleutrade.py
ccxt/braziliex.py
ccxt/btcalpha.py
ccxt/btcbox.py
ccxt/btcchina.py
ccxt/btcexchange.py
ccxt/btcmarkets.py
ccxt/btctradeim.py
ccxt/btctradeua.py
ccxt/btcturk.py
ccxt/buda.py
ccxt/bxinth.py
ccxt/bybit.py
ccxt/ccex.py
ccxt/cex.py
ccxt/chbtc.py
ccxt/chilebit.py
ccxt/cobinhood.py
ccxt/coinbase.py
ccxt/coinbaseprime.py
ccxt/coinbasepro.py
ccxt/coincheck.py
ccxt/coinegg.py
ccxt/coinex.py
ccxt/coinexchange.py
ccxt/coinfalcon.py
ccxt/coinfloor.py
ccxt/coingecko.py
ccxt/coingi.py
ccxt/coinhe.py
ccxt/coinmarketcap.py
ccxt/coinmate.py
ccxt/coinnest.py
ccxt/coinone.py
ccxt/coinspot.py
ccxt/coinstore.py
ccxt/cointiger.py
ccxt/coolcoin.py
ccxt/coss.py
ccxt/crex24.py
ccxt/crypton.py
ccxt/cryptopia.py
ccxt/deribit.py
ccxt/digifinex.py
ccxt/dsx.py
ccxt/dx.py
ccxt/ethfinex.py
ccxt/exmo.py
ccxt/exx.py
ccxt/fcoin.py
ccxt/fcoinjp.py
ccxt/flowbtc.py
ccxt/foxbit.py
ccxt/ftx.py
ccxt/fybse.py
ccxt/fybsg.py
ccxt/gatecoin.py
ccxt/gateio.py
ccxt/gdax.py
ccxt/gemini.py
ccxt/getbtc.py
ccxt/hadax.py
ccxt/hitbtc.py
ccxt/hitbtc2.py
ccxt/huobi.py
ccxt/huobicny.py
ccxt/huobipro.py
ccxt/huobiru.py
ccxt/ice3x.py
ccxt/idex.py
ccxt/independentreserve.py
ccxt/indodax.py
ccxt/itbit.py
ccxt/jubi.py
ccxt/kkex.py
ccxt/kraken.py
ccxt/kucoin.py
ccxt/kucoin2.py
ccxt/kuna.py
ccxt/lakebtc.py
ccxt/latoken.py
ccxt/lbank.py
ccxt/liqui.py
ccxt/liquid.py
ccxt/livecoin.py
ccxt/luno.py
ccxt/lykke.py
ccxt/mandala.py
ccxt/mercado.py
ccxt/mixcoins.py
la_v000871-1.88.1133.dist-info/LICENSE.txt
la_v000871-1.88.1133.dist-info/METADATA
la_v000871-1.88.1133.dist-info/WHEEL
la_v000871-1.88.1133.dist-info/top_level.txt
la_v000871-1.88.1133.dist-info/RECORD
